odoo/addons/ssi_stock/README.rst
odoo/addons/ssi_stock/__init__.py
odoo/addons/ssi_stock/__manifest__.py
odoo/addons/ssi_stock/menu.xml
odoo/addons/ssi_stock/data/approval_template_data.xml
odoo/addons/ssi_stock/data/base_automation_data.xml
odoo/addons/ssi_stock/data/ir_actions_server_data.xml
odoo/addons/ssi_stock/data/location_type_data.xml
odoo/addons/ssi_stock/data/policy_template_data.xml
odoo/addons/ssi_stock/data/stock_picking_type_category_data.xml
odoo/addons/ssi_stock/i18n/ssi_stock.pot
odoo/addons/ssi_stock/models/__init__.py
odoo/addons/ssi_stock/models/location_type.py
odoo/addons/ssi_stock/models/mixin_picking_type_category_m2o_configurator.py
odoo/addons/ssi_stock/models/mixin_picking_type_m2o_configurator.py
odoo/addons/ssi_stock/models/picking_type_category.py
odoo/addons/ssi_stock/models/product_category.py
odoo/addons/ssi_stock/models/product_product.py
odoo/addons/ssi_stock/models/stock_inventory.py
odoo/addons/ssi_stock/models/stock_location.py
odoo/addons/ssi_stock/models/stock_move.py
odoo/addons/ssi_stock/models/stock_move_line.py
odoo/addons/ssi_stock/models/stock_picking.py
odoo/addons/ssi_stock/models/stock_picking_type.py
odoo/addons/ssi_stock/models/stock_production_lot.py
odoo/addons/ssi_stock/models/stock_quant.py
odoo/addons/ssi_stock/models/stock_rule.py
odoo/addons/ssi_stock/models/stock_warehouse.py
odoo/addons/ssi_stock/security/ir.model.access.csv
odoo/addons/ssi_stock/security/ir_module_category_data.xml
odoo/addons/ssi_stock/security/res_group_data.xml
odoo/addons/ssi_stock/static/description/icon.png
odoo/addons/ssi_stock/templates/picking_type_category_m2_configurator_templates.xml
odoo/addons/ssi_stock/templates/picking_type_m2_configurator_templates.xml
odoo/addons/ssi_stock/views/adjustment_in_views.xml
odoo/addons/ssi_stock/views/adjustment_out_views.xml
odoo/addons/ssi_stock/views/consume_views.xml
odoo/addons/ssi_stock/views/delivery_order_views.xml
odoo/addons/ssi_stock/views/goods_receipt_views.xml
odoo14_addon_ssi_stock-14.0.8.2.1.dist-info/METADATA
odoo14_addon_ssi_stock-14.0.8.2.1.dist-info/WHEEL
odoo14_addon_ssi_stock-14.0.8.2.1.dist-info/top_level.txt
odoo14_addon_ssi_stock-14.0.8.2.1.dist-info/RECORD
