Metadata-Version: 2.1
Name: odoo14-addon-ssi_stock
Version: 14.0.8.2.1
Summary: Inventory
Home-page: https://simetri-sinergi.id
Author: PT. Simetri Sinergi Indonesia, OpenSynergy Indonesia
License: AGPL-3
Classifier: Programming Language :: Python
Classifier: Framework :: Odoo
Classifier: Framework :: Odoo :: 14.0
Classifier: License :: OSI Approved :: GNU Affero General Public License v3
Requires-Python: >=3.6
Requires-Dist: odoo14-addon-ssi-master-data-mixin
Requires-Dist: odoo14-addon-ssi-multiple-approval-mixin
Requires-Dist: odoo14-addon-ssi-policy-mixin
Requires-Dist: odoo14-addon-ssi-print-mixin
Requires-Dist: odoo14-addon-ssi-product
Requires-Dist: odoo14-addon-stock-inventory-preparation-filter
Requires-Dist: odoo14-addon-stock-move-backdating
Requires-Dist: odoo14-addon-stock-move-line-auto-fill
Requires-Dist: odoo<14.1dev,>=14.0a
